{
  "name": "The 2021 Train Collection",
  "content": {
    "Covert Skins": [
      {
        "name": "Glock-18 | Gamma Doppler",
        "can_be_souvenir": false,
        "can_be_stattrak": false,
        "wears": {
          "min_wear": 0,
          "max_wear": 0.5
        },
        "prices": {
          "Factory New": "50.16",
          "Minimal Wear": "40.79",
          "Field-Tested": "34.34",
          "Well-Worn": "37.67",
          "Battle-Scarred": "38.18"
        }
      },
      {
        "name": "M4A4 | The Coalition",
        "can_be_souvenir": false,
        "can_be_stattrak": false,
        "wears": {
          "min_wear": 0,
          "max_wear": 1
        },
        "prices": {
          "Factory New": "279.00",
          "Minimal Wear": "59.01",
          "Field-Tested": "21.00",
          "Well-Worn": "9.38",
          "Battle-Scarred": "7.50"
        }
      }
    ],
    "Classified Skins": [
      {
        "name": "MAC-10 | Propaganda",
        "can_be_souvenir": false,
        "can_be_stattrak": false,
        "wears": {
          "min_wear": 0,
          "max_wear": 0.62
        },
        "prices": {
          "Factory New": "34.80",
          "Minimal Wear": "29.50",
          "Field-Tested": "24.05",
          "Well-Worn": "20.65",
          "Battle-Scarred": "19.78"
        }
      },
      {
        "name": "FAMAS | Meltdown",
        "can_be_souvenir": false,
        "can_be_stattrak": false,
        "wears": {
          "min_wear": 0,
          "max_wear": 0.4
        },
        "prices": {
          "Factory New": "32.36",
          "Minimal Wear": "28.09",
          "Field-Tested": "25.00",
          "Well-Worn": "24.34"
        }
      },
      {
        "name": "USP-S | Whiteout",
        "can_be_souvenir": false,
        "can_be_stattrak": false,
        "wears": {
          "min_wear": 0.06,
          "max_wear": 0.8
        },
        "prices": {
          "Factory New": "190.00",
          "Minimal Wear": "44.04",
          "Field-Tested": "23.61",
          "Well-Worn": "22.44",
          "Battle-Scarred": "20.93"
        }
      }
    ],
    "Restricted Skins": [
      {
        "name": "Nova | Red Quartz",
        "can_be_souvenir": false,
        "can_be_stattrak": false,
        "wears": {
          "min_wear": 0,
          "max_wear": 0.4
        },
        "prices": {
          "Factory New": "7.51",
          "Minimal Wear": "4.60",
          "Field-Tested": "3.74",
          "Well-Worn": "4.13"
        }
      },
      {
        "name": "CZ75-Auto | Syndicate",
        "can_be_souvenir": false,
        "can_be_stattrak": false,
        "wears": {
          "min_wear": 0,
          "max_wear": 0.7
        },
        "prices": {
          "Factory New": "6.47",
          "Minimal Wear": "4.51",
          "Field-Tested": "3.54",
          "Well-Worn": "3.67",
          "Battle-Scarred": "3.42"
        }
      },
      {
        "name": "AWP | POP AWP",
        "can_be_souvenir": false,
        "can_be_stattrak": false,
        "wears": {
          "min_wear": 0,
          "max_wear": 0.44
        },
        "prices": {
          "Factory New": "6.50",
          "Minimal Wear": "4.39",
          "Field-Tested": "3.20",
          "Well-Worn": "3.58"
        }
      },
      {
        "name": "P2000 | Space Race",
        "can_be_souvenir": false,
        "can_be_stattrak": false,
        "wears": {
          "min_wear": 0,
          "max_wear": 0.6
        },
        "prices": {
          "Factory New": "6.84",
          "Minimal Wear": "4.72",
          "Field-Tested": "3.72",
          "Well-Worn": "3.75",
          "Battle-Scarred": "3.72"
        }
      },
      {
        "name": "MP5-SD | Autumn Twilly",
        "can_be_souvenir": false,
        "can_be_stattrak": false,
        "wears": {
          "min_wear": 0,
          "max_wear": 0.58
        },
        "prices": {
          "Factory New": "6.94",
          "Minimal Wear": "4.55",
          "Field-Tested": "3.62",
          "Well-Worn": "4.27",
          "Battle-Scarred": "3.97"
        }
      }
    ],
    "Mil-Spec Skins": [
      {
        "name": "Desert Eagle | Sputnik",
        "can_be_souvenir": false,
        "can_be_stattrak": false,
        "wears": {
          "min_wear": 0,
          "max_wear": 0.5
        },
        "prices": {
          "Factory New": "1.90",
          "Minimal Wear": "1.16",
          "Field-Tested": "0.92",
          "Well-Worn": "0.91",
          "Battle-Scarred": "0.88"
        }
      },
      {
        "name": "Tec-9 | Safety Net",
        "can_be_souvenir": false,
        "can_be_stattrak": false,
        "wears": {
          "min_wear": 0,
          "max_wear": 0.6
        },
        "prices": {
          "Factory New": "1.34",
          "Minimal Wear": "1.18",
          "Field-Tested": "0.92",
          "Well-Worn": "0.88",
          "Battle-Scarred": "0.80"
        }
      },
      {
        "name": "M4A1-S | Fizzy POP",
        "can_be_souvenir": false,
        "can_be_stattrak": false,
        "wears": {
          "min_wear": 0,
          "max_wear": 0.57
        },
        "prices": {
          "Factory New": "1.86",
          "Minimal Wear": "1.13",
          "Field-Tested": "0.79",
          "Well-Worn": "0.87",
          "Battle-Scarred": "0.81"
        }
      },
      {
        "name": "R8 Revolver | Blaze",
        "can_be_souvenir": false,
        "can_be_stattrak": false,
        "wears": {
          "min_wear": 0,
          "max_wear": 0.08
        },
        "prices": {
          "Factory New": "1.28",
          "Minimal Wear": "1.28"
        }
      },
      {
        "name": "SSG 08 | Spring Twilly",
        "can_be_souvenir": false,
        "can_be_stattrak": false,
        "wears": {
          "min_wear": 0,
          "max_wear": 0.55
        },
        "prices": {
          "Factory New": "1.11",
          "Minimal Wear": "1.10",
          "Field-Tested": "0.90",
          "Well-Worn": "0.85",
          "Battle-Scarred": "1.10"
        }
      },
      {
        "name": "UMP-45 | Full Stop",
        "can_be_souvenir": false,
        "can_be_stattrak": false,
        "wears": {
          "min_wear": 0,
          "max_wear": 0.6
        },
        "prices": {
          "Factory New": "1.33",
          "Minimal Wear": "1.08",
          "Field-Tested": "0.86",
          "Well-Worn": "0.98",
          "Battle-Scarred": "1.05"
        }
      },
      {
        "name": "AUG | Amber Fade",
        "can_be_souvenir": false,
        "can_be_stattrak": false,
        "wears": {
          "min_wear": 0,
          "max_wear": 0.4
        },
        "prices": {
          "Factory New": "1.24",
          "Minimal Wear": "0.76",
          "Field-Tested": "0.95",
          "Well-Worn": "1.13"
        }
      }
    ],
    "Industrial Grade Skins": [],
    "Consumer Grade Skins": []
  }
}